external_log_connector/__init__.py
external_log_connector/lmc_external_log_connector.py
external_log_connector-0.1.2.dist-info/METADATA
external_log_connector-0.1.2.dist-info/WHEEL
external_log_connector-0.1.2.dist-info/top_level.txt
external_log_connector-0.1.2.dist-info/RECORD
