Metadata-Version: 2.4
Name: external-log-connector
Version: 0.1.2
Summary: A logging-enhanced RemoteConnector similar to BlackholeConnector
Author-email: Baoloongmao <baoloongmao@tencent.com>
License: Apache-2.0
Requires-Python: >=3.8
Requires-Dist: lmcache>=0.1.0
